rtl/vhdl/mu0_behav.vhd
library IEEE;
use STD.textio.all;
use IEEE.std_logic_1164.all;
use IEEE.numeric_std.all;
use WORK.std_logic_textio.all;


entity mu0 is
  generic (
    MAXWIDTH : integer := 16;
    MAXDEPTH : integer := 12
  );
  port (
    clk      : in  std_logic;
    reset    : in  std_logic;
    pc       : out std_logic_vector(MAXWIDTH-1 downto 0);
    ir       : out std_logic_vector(MAXWIDTH-1 downto 0);
    acc      : out std_logic_vector(MAXWIDTH-1 downto 0)
  );
end entity mu0;

architecture behavioral of mu0 is 
  -- Type declarations.
  type mem_type is array(0 to 2**MAXDEPTH-1) of 
    std_logic_vector(MAXWIDTH-1 downto 0);
  -- According to XST User Manual, v14.1, p. 239.
  impure function InitRamFromFile(RamFileName : in string) 
    return mem_type is
    FILE RamFile : text is in RamFileName;
    variable RamFileLine : line;
    variable ram : mem_type;
  begin
    for i in mem_type'RANGE loop
      readline(RamFile, RamFileLine);
      hread(RamFileLine, ram(i));
    end loop;
    return ram;
  end function InitRamFromFile;
  -- Constant declarations.
  constant LDA : std_logic_vector(3 downto 0) := "0000"; 
  constant STO : std_logic_vector(3 downto 0) := "0001"; 
  constant ADD : std_logic_vector(3 downto 0) := "0010"; 
  constant SUB : std_logic_vector(3 downto 0) := "0011"; 
  constant JMP : std_logic_vector(3 downto 0) := "0100"; 
  constant JGE : std_logic_vector(3 downto 0) := "0101"; 
  constant JNE : std_logic_vector(3 downto 0) := "0110"; 
  constant STP : std_logic_vector(3 downto 0) := "0111"; 
  -- Signal declarations.
  signal opcode   : std_logic_vector(MAXWIDTH-1 downto MAXWIDTH-4);
  signal address  : std_logic_vector(MAXWIDTH-5 downto 0);
  -- Initialize memory using impure function.
  signal mem      : mem_type := InitRamFromFile("prog.lst");
  signal pc_reg   : std_logic_vector(MAXWIDTH-1 downto 0);
  signal pc_next  : std_logic_vector(MAXWIDTH-1 downto 0);
  signal ir_reg   : std_logic_vector(MAXWIDTH-1 downto 0);
  signal ir_next  : std_logic_vector(MAXWIDTH-1 downto 0);
  signal acc_reg  : std_logic_vector(MAXWIDTH-1 downto 0);
  signal acc_next : std_logic_vector(MAXWIDTH-1 downto 0);
begin

  -- Synchronous logic.
  process (clk, reset)
  begin
    if (reset = '1') then
      pc_reg  <= (others => '0');
      ir_reg  <= (others => '0');
      acc_reg <= (others => '0');
    elsif (rising_edge(clk)) then
      pc_reg  <= pc_next;
      ir_reg  <= ir_next;
      acc_reg <= acc_next;
    end if;
  end process;

  -- Combinational logic.
  process (
    pc_reg, pc_next,
    ir_reg, ir_next,
    acc_reg, acc_next
  )
    variable opcode_v : std_logic_vector(3 downto 0);
  begin
    pc_next  <= pc_reg;
    ir_next  <= ir_reg;
    acc_next <= acc_reg;
    --    
    opcode  <= ir_reg(MAXWIDTH-1 downto MAXWIDTH-4);
    address <= ir_reg(MAXWIDTH-5 downto 0);
    opcode_v := opcode;
    case (opcode_v) is
      when LDA => 
        acc_next <= mem(to_integer(unsigned(address)));
      when STO =>
        mem(to_integer(unsigned(address))) <= acc_reg;
      when ADD =>
        acc_next <= std_logic_vector(unsigned(acc_reg) + 
                    unsigned(mem(to_integer(unsigned(address)))));
      when SUB =>
        acc_next <= std_logic_vector(unsigned(acc_reg) - 
                    unsigned(mem(to_integer(unsigned(address)))));
      when JMP =>
        pc_next  <= (MAXWIDTH-1 downto MAXWIDTH-4 => '0') & address;
      when JNE =>
        if (acc_reg /= std_logic_vector(to_unsigned(0,MAXWIDTH))) then
          pc_next <= (MAXWIDTH-1 downto MAXWIDTH-4 => '0') & address;
        end if;
      when JGE =>
        if (acc_reg(MAXWIDTH-1) = '0') then
          pc_next <= (MAXWIDTH-1 downto MAXWIDTH-4 => '0') & address;
        end if;
      when STP =>
        pc_next <= pc_reg;
      when others =>
        pc_next <= pc_reg;
    end case;
    --
    ir_next  <= mem(to_integer(unsigned(pc_reg)));
    if (ir_reg(MAXWIDTH-1 downto MAXWIDTH-4) /= STP) then
      pc_next <= std_logic_vector(unsigned(pc_reg) + 1);
    end if;    
  end process;
    
  -- Assign outputs.
  pc  <= pc_reg;
  ir  <= ir_reg;
  acc <= acc_reg;

end architecture behavioral;

bench/verilog/mu0_tb.v
`timescale 1 ns/1 ps

module mu0_tb;
  parameter MAXWIDTH = 16, MAXDEPTH = 12;
  parameter STP = 4'b0111;
  parameter CLK_PERIOD=10/*ns*/;
  reg clk, reset;
  wire [MAXWIDTH-1:0] pc;
  wire [MAXWIDTH-1:0] ir;
  wire [MAXWIDTH-1:0] acc;

  mu0 uut (
    .clk(clk), 
    .reset(reset),
    .pc(pc), 
    .ir(ir), 
    .acc(acc)
  );

  // Test clock generation.
  //
  // Clock pulse starts from 0.
  initial
  begin
    clk   = 1'b0;
    reset = 1'b1;
    #(CLK_PERIOD) reset = 1'b0;
  end
  // Free-running clock
  always
    #(CLK_PERIOD/2) clk = ~clk;

  // Write simulation data to a VCD waveform file.
  initial
  begin
    // Open a VCD file for writing
    $dumpfile("mu0.vcd");
    // Dump the values of all nets and wires in module "gcd_main", seen
    // from hierarchy level 0
    $dumpvars(0, mu0_tb);
  end

  always
  begin
    #(CLK_PERIOD);
    // Detect STOP/STP opcode.
    if (ir[MAXWIDTH-1:MAXWIDTH-4] == STP) 
    begin
      // Automatic end of the current simulation.
      $display("End simulation time reached.");
      $finish;
    end
  end

endmodule

sim/rtl_sim/out/mu0_behavioral.vcd
$comment
	File created using the following command:
		vcd file mu0_behavioral.vcd -dumpports -unique
$end
$date
	Thu Nov 13 22:40:01 2014
$end
$version
	dumpports ModelSim Version 10.1d
$end
$timescale
	1ps
$end
$scope module mu0_tb $end
$scope module uut $end
$var port 1 <0 clk $end
$var port 1 <1 reset $end
$var port 1 <2 pc [15] $end
$var port 1 <3 pc [14] $end
$var port 1 <4 pc [13] $end
$var port 1 <5 pc [12] $end
$var port 1 <6 pc [11] $end
$var port 1 <7 pc [10] $end
$var port 1 <8 pc [9] $end
$var port 1 <9 pc [8] $end
$var port 1 <10 pc [7] $end
$var port 1 <11 pc [6] $end
$var port 1 <12 pc [5] $end
$var port 1 <13 pc [4] $end
$var port 1 <14 pc [3] $end
$var port 1 <15 pc [2] $end
$var port 1 <16 pc [1] $end
$var port 1 <17 pc [0] $end
$var port 1 <18 ir [15] $end
$var port 1 <19 ir [14] $end
$var port 1 <20 ir [13] $end
$var port 1 <21 ir [12] $end
$var port 1 <22 ir [11] $end
$var port 1 <23 ir [10] $end
$var port 1 <24 ir [9] $end
$var port 1 <25 ir [8] $end
$var port 1 <26 ir [7] $end
$var port 1 <27 ir [6] $end
$var port 1 <28 ir [5] $end
$var port 1 <29 ir [4] $end
$var port 1 <30 ir [3] $end
$var port 1 <31 ir [2] $end
$var port 1 <32 ir [1] $end
$var port 1 <33 ir [0] $end
$var port 1 <34 acc [15] $end
$var port 1 <35 acc [14] $end
$var port 1 <36 acc [13] $end
$var port 1 <37 acc [12] $end
$var port 1 <38 acc [11] $end
$var port 1 <39 acc [10] $end
$var port 1 <40 acc [9] $end
$var port 1 <41 acc [8] $end
$var port 1 <42 acc [7] $end
$var port 1 <43 acc [6] $end
$var port 1 <44 acc [5] $end
$var port 1 <45 acc [4] $end
$var port 1 <46 acc [3] $end
$var port 1 <47 acc [2] $end
$var port 1 <48 acc [1] $end
$var port 1 <49 acc [0] $end
$upscope $end
$upscope $end
$enddefinitions $end
#0
$dumpports
pX 6 6 <17
pX 6 6 <16
pX 6 6 <15
pX 6 6 <14
pX 6 6 <13
pX 6 6 <12
pX 6 6 <11
pX 6 6 <10
pX 6 6 <9
pX 6 6 <8
pX 6 6 <7
pX 6 6 <6
pX 6 6 <5
pX 6 6 <4
pX 6 6 <3
pX 6 6 <2
pX 6 6 <33
pX 6 6 <32
pX 6 6 <31
pX 6 6 <30
pX 6 6 <29
pX 6 6 <28
pX 6 6 <27
pX 6 6 <26
pX 6 6 <25
pX 6 6 <24
pX 6 6 <23
pX 6 6 <22
pX 6 6 <21
pX 6 6 <20
pX 6 6 <19
pX 6 6 <18
pX 6 6 <49
pX 6 6 <48
pX 6 6 <47
pX 6 6 <46
pX 6 6 <45
pX 6 6 <44
pX 6 6 <43
pX 6 6 <42
pX 6 6 <41
pX 6 6 <40
pX 6 6 <39
pX 6 6 <38
pX 6 6 <37
pX 6 6 <36
pX 6 6 <35
pX 6 6 <34
pU 0 6 <1
pD 6 0 <0
$end
#5000
pU 0 6 <0
pL 6 0 <49
pL 6 0 <48
pL 6 0 <47
pL 6 0 <46
pL 6 0 <45
pL 6 0 <44
pL 6 0 <43
pL 6 0 <42
pL 6 0 <41
pL 6 0 <40
pL 6 0 <39
pL 6 0 <38
pL 6 0 <37
pL 6 0 <36
pL 6 0 <35
pL 6 0 <34
pL 6 0 <17
pL 6 0 <16
pL 6 0 <15
pL 6 0 <14
pL 6 0 <13
pL 6 0 <12
pL 6 0 <11
pL 6 0 <10
pL 6 0 <9
pL 6 0 <8
pL 6 0 <7
pL 6 0 <6
pL 6 0 <5
pL 6 0 <4
pL 6 0 <3
pL 6 0 <2
pL 6 0 <33
pL 6 0 <32
pL 6 0 <31
pL 6 0 <30
pL 6 0 <29
pL 6 0 <28
pL 6 0 <27
pL 6 0 <26
pL 6 0 <25
pL 6 0 <24
pL 6 0 <23
pL 6 0 <22
pL 6 0 <21
pL 6 0 <20
pL 6 0 <19
pL 6 0 <18
pH 0 6 <47
#10000
pD 6 0 <1
pD 6 0 <0
#15000
pU 0 6 <0
pH 0 6 <17
pH 0 6 <31
pH 0 6 <48
pL 6 0 <47
pH 0 6 <46
#20000
pD 6 0 <0
#25000
pU 0 6 <0
pL 6 0 <17
pH 0 6 <16
pH 0 6 <33
pH 0 6 <20
pH 0 6 <49
#30000
pD 6 0 <0
#35000
pU 0 6 <0
pH 0 6 <17
pL 6 0 <33
pH 0 6 <32
pH 0 6 <21
pL 6 0 <20
#40000
pD 6 0 <0
#45000
pU 0 6 <0
pL 6 0 <32
pL 6 0 <31
pH 0 6 <20
pH 0 6 <19
$vcdclose
